archive/__init__.py
archive/listener.py
robotframework_listener_archive_output-0.0.4.dist-info/AUTHORS.rst
robotframework_listener_archive_output-0.0.4.dist-info/LICENSE
robotframework_listener_archive_output-0.0.4.dist-info/METADATA
robotframework_listener_archive_output-0.0.4.dist-info/WHEEL
robotframework_listener_archive_output-0.0.4.dist-info/top_level.txt
robotframework_listener_archive_output-0.0.4.dist-info/RECORD
